[
  {
    "name": "Abarth",
    "slug": "abarth",
    "image": {
      "src": "./optimized/abarth.webp"
    }
  },
  {
    "name": "Aixam",
    "slug": "aixam",
    "image": {
      "src": "./optimized/aixam.webp"
    }
  },
  {
    "name": "Alfa Romeo",
    "slug": "alfa-romeo",
    "image": {
      "src": "./optimized/alfa-romeo.webp"
    }
  },
  {
    "name": "Alpine",
    "slug": "alpine",
    "image": {
      "src": "./optimized/alpine.webp"
    }
  },
  {
    "name": "Aston Martin",
    "slug": "aston-martin",
    "image": {
      "src": "./optimized/aston-martin.webp"
    }
  },
  {
    "name": "Audi",
    "slug": "audi",
    "image": {
      "src": "./optimized/audi.webp"
    }
  },
  {
    "name": "Bentley",
    "slug": "bentley",
    "image": {
      "src": "./optimized/bentley.webp"
    }
  }, 
  {
    "name": "BMW",
    "slug": "bmw",
    "image": {
      "src": "./optimized/bmw.webp"
    }
  },
  {
    "name": "Bugatti",
    "slug": "bugatti",
    "image": {
      "src": "./optimized/bugatti.webp"
    }
  },
  {
    "name": "BYD",
    "slug": "byd",
    "image": {
      "src": "./optimized/byd.webp"
    }
  },

  {
    "name": "Cadillac",
    "slug": "cadillac",
    "image": {
      "src": "./optimized/cadillac.webp"
    }
  },
  {
    "name": "Chevrolet",
    "slug": "chevrolet",
    "image": {
      "src": "./optimized/chevrolet.webp"
    }
  },
  {
    "name": "Chrysler",
    "slug": "chrysler",
    "image": {
      "src": "./optimized/chrysler.webp"
    }
  },
  {
    "name": "Citroën",
    "slug": "citroen",
    "image": {
      "src": "./optimized/citroen.webp"
    }
  },
  {
    "name": "Cupra",
    "slug": "cupra",
    "image": {
      "src": "./optimized/cupra.webp"
    }
  },
  {
    "name": "Dacia",
    "slug": "dacia",
    "image": {
      "src": "./optimized/dacia.webp"
    }
  },
  {
    "name": "DAF",
    "slug": "daf",
    "image": {
      "src": "./optimized/daf.webp"
    }
  },
  {
    "name": "Dodge",
    "slug": "dodge",
    "image": {
      "src": "./optimized/dodge.webp"
    }
  },
  {
    "name": "DS",
    "slug": "ds",
    "image": {
      "src": "./optimized/ds.webp"
    }
  },
  {
    "name": "Ferrari",
    "slug": "ferrari",
    "image": {
      "src": "./optimized/ferrari.webp"
    }
  },
  {
    "name": "Fiat",
    "slug": "fiat",
    "image": {
      "src": "./optimized/fiat.webp"
    }
  },
  {
    "name": "Ford",
    "slug": "ford",
    "image": {
      "src": "./optimized/ford.webp"
    }
  },
  {
    "name": "Gillet",
    "slug": "gillet",
    "image": {
      "src": "./optimized/gillet.webp"
    }
  },
  {
    "name": "GMC",
    "slug": "gmc",
    "image": {
      "src": "./optimized/gmc.webp"
    }
  },
  {
    "name": "Honda",
    "slug": "honda",
    "image": {
      "src": "./optimized/honda.webp"
    }
  },  
  {
    "name": "Hummer",
    "slug": "hummer",
    "image": {
      "src": "./optimized/hummer.webp"
    }
  },
  {
    "name": "Hyundai",
    "slug": "hyundai",
    "image": {
      "src": "./optimized/hyundai.webp"
    }
  },
  {
    "name": "Infiniti",
    "slug": "infiniti",
    "image": {
      "src": "./optimized/infiniti.webp"
    }
  },
  {
    "name": "Isuzu",
    "slug": "isuzu",
    "image": {
      "src": "./optimized/isuzu.webp"
    }
  },
  {
    "name": "Iveco",
    "slug": "iveco",
    "image": {
      "src": "./optimized/iveco.webp"
    }
  },
  {
    "name": "Jaguar",
    "slug": "jaguar",
    "image": {
      "src": "./optimized/jaguar.webp"
    }
  },
  {
    "name": "Jeep",
    "slug": "jeep",
    "image": {
      "src": "./optimized/jeep.webp"
    }
  },  
  {
    "name": "Kia",
    "slug": "kia",
    "image": {
      "src": "./optimized/kia.webp"
    }
  },
  {
    "name": "Koenigsegg",
    "slug": "koenigsegg",
    "image": {
      "src": "./optimized/koenigsegg.webp"
    }
  },
  {
    "name": "KTM",
    "slug": "ktm",
    "image": {
      "src": "./optimized/ktm.webp"
    }
  },
  {
    "name": "Lada",
    "slug": "lada",
    "image": {
      "src": "./optimized/lada.webp"
    }
  },
  {
    "name": "Lamborghini",
    "slug": "lamborghini",
    "image": {
      "src": "./optimized/lamborghini.webp"
    }
  },
  {
    "name": "Land Rover",
    "slug": "land-rover",
    "image": {
      "src": "./optimized/land-rover.webp"
    }
  },
  {
    "name": "Leapmotor",
    "slug": "leapmotor",
    "image": {
      "src": "./optimized/leapmotor.webp"
    }
  },
  {
    "name": "Lexus",
    "slug": "lexus",
    "image": {
      "src": "./optimized/lexus.webp"
    }
  },
  {
    "name": "Ligier",
    "slug": "ligier",
    "image": {
      "src": "./optimized/ligier.webp"
    }
  },
  {
    "name": "Lotus",
    "slug": "lotus",
    "image": {
      "src": "./optimized/lotus.webp"
    }
  },
  {
    "name": "Lynk & Co",
    "slug": "lynk-and-co",
    "image": {
      "src": "./optimized/lynk-and-co.webp"
    }
  },
  {
    "name": "Mack",
    "slug": "mack",
    "image": {
      "src": "./optimized/mack.webp"
    }
  },
  {
    "name": "MAN",
    "slug": "man",
    "image": {
      "src": "./optimized/man.webp"
    }
  },
  {
    "name": "Maserati",
    "slug": "maserati",
    "image": {
      "src": "./optimized/maserati.webp"
    }
  },
  {
    "name": "Maxus",
    "slug": "maxus",
    "image": {
      "src": "./optimized/maxus.webp"
    }
  },
  {
    "name": "Maybach",
    "slug": "maybach",
    "image": {
      "src": "./optimized/maybach.webp"
    }
  },
  {
    "name": "Mazda",
    "slug": "mazda",
    "image": {
      "src": "./optimized/mazda.webp"
    }
  },
  {
    "name": "McLaren",
    "slug": "mclaren",
    "image": {
      "src": "./optimized/mclaren.webp"
    }
  },
  {
    "name": "Mercedes-Benz",
    "slug": "mercedes-benz",
    "image": {
      "src": "./optimized/mercedes-benz.webp"
    }
  },
  {
    "name": "MG",
    "slug": "mg",
    "image": {
      "src": "./optimized/mg.webp"
    }
  },
  {
    "name": "Microcar",
    "slug": "microcar",
    "image": {
      "src": "./optimized/microcar.webp"
    }
  },
  {
    "name": "Mini",
    "slug": "mini",
    "image": {
      "src": "./optimized/mini.webp"
    }
  },
  {
    "name": "Mitsubishi",
    "slug": "mitsubishi",
    "image": {
      "src": "./optimized/mitsubishi.webp"
    }
  },
  {
    "name": "NIO",
    "slug": "nio",
    "image": {
      "src": "./optimized/nio.webp"
    }
  },
  {
    "name": "Nissan",
    "slug": "nissan",
    "image": {
      "src": "./optimized/nissan.webp"
    }
  },
  {
    "name": "Opel",
    "slug": "opel",
    "image": {
      "src": "./optimized/opel.webp"
    }
  },
  {
    "name": "Pagani",
    "slug": "pagani",
    "image": {
      "src": "./optimized/pagani.webp"
    }
  },
  {
    "name": "Peugeot",
    "slug": "peugeot",
    "image": {
      "src": "./optimized/peugeot.webp"
    }
  },
  {
    "name": "Polestar",
    "slug": "polestar",
    "image": {
      "src": "./optimized/polestar.webp"
    }
  },
  {
    "name": "Pontiac",
    "slug": "pontiac",
    "image": {
      "src": "./optimized/pontiac.webp"
    }
  },
  {
    "name": "Porsche",
    "slug": "porsche",
    "image": {
      "src": "./optimized/porsche.webp"
    }
  },
  {
    "name": "RAM",
    "slug": "ram",
    "image": {
      "src": "./optimized/ram.webp"
    }
  },
  {
    "name": "Renault",
    "slug": "renault",
    "image": {
      "src": "./optimized/renault.webp"
    }
  },
  {
    "name": "Rolls-Royce",
    "slug": "rolls-royce",
    "image": {
      "src": "./optimized/rolls-royce.webp"
    }
  },
  {
    "name": "Scania",
    "slug": "scania",
    "image": {
      "src": "./optimized/scania.webp"
    }
  },
  {
    "name": "SEAT",
    "slug": "seat",
    "image": {
      "src": "./optimized/seat.webp"
    }
  },
  {
    "name": "Škoda",
    "slug": "skoda",
    "image": {
      "src": "./optimized/skoda.webp"
    }
  },
  {
    "name": "Smart",
    "slug": "smart",
    "image": {
      "src": "./optimized/smart.webp"
    }
  },
  {
    "name": "SsangYong",
    "slug": "ssangyong",
    "image": {
      "src": "./optimized/ssangyong.webp"
    }
  },
  {
    "name": "Subaru",
    "slug": "subaru",
    "image": {
      "src": "./optimized/subaru.webp"
    }
  },
  {
    "name": "Suzuki",
    "slug": "suzuki",
    "image": {
      "src": "./optimized/suzuki.webp"
    }
  },
  {
    "name": "Tesla",
    "slug": "tesla",
    "image": {
      "src": "./optimized/tesla.webp"
    }
  },
  {
    "name": "Toyota",
    "slug": "toyota",
    "image": {
      "src": "./optimized/toyota.webp"
    }
  },
  {
    "name": "Volkswagen",
    "slug": "volkswagen",
    "image": {
      "src": "./optimized/volkswagen.webp"
    }
  },
  {
    "name": "Volvo",
    "slug": "volvo",
    "image": {
      "src": "./optimized/volvo.webp"
    }
  },
  {
    "name": "WEY",
    "slug": "wey",
    "image": {
      "src": "./optimized/wey.webp"
    }
  },
  {
    "name": "XPeng",
    "slug": "xpeng",
    "image": {
      "src": "./optimized/xpeng.webp"
    }
  },
  {
    "name": "Zeekr",
    "slug": "zeekr",
    "image": {
      "src": "./optimized/zeekr.webp"
    }
  }
]
